{
	"愛戴": "ㄞˋㄉㄞˋ",
	"愛國": "ㄞˋㄍㄨㄛˊ",
	"愛滋病": "ㄞˋㄗ_ㄅㄧㄥˋ",
	"安頓": "ㄢ_ㄉㄨㄣˋ",
	"安撫": "ㄢ_ㄈㄨˇ",
	"安寧": "ㄢ_ㄋㄧㄥˊ",
	"安詳": "ㄢ_ㄒㄧㄤˊ",
	"安置": "ㄢ_ㄓˋ",
	"暗暗": "ㄢˋㄢˋ",
	"案件": "ㄢˋㄐㄧㄢˋ",
	"案情": "ㄢˋㄑㄧㄥˊ",
	"按摩": "ㄢˋㄇㄛˊ",
	"昂貴": "ㄤˊㄍㄨㄟˋ",
	"奧妙": "ㄠˋㄇㄧㄠˋ",
	"懊惱": "ㄠˋㄋㄠˇ",
	"八卦": "ㄅㄚ_ㄍㄨㄚˋ",
	"八字": "ㄅㄚ_ㄗˋ",
	"把持": "ㄅㄚˇㄔˊ",
	"把手": "ㄅㄚˇㄕㄡˇ",
	"白皮書": "ㄅㄞˊㄆㄧˊㄕㄨ_",
	"拜會": "ㄅㄞˋㄏㄨㄟˋ",
	"頒發": "ㄅㄢ_ㄈㄚ_",
	"頒獎": "ㄅㄢ_ㄐㄧㄤˇ",
	"辦案": "ㄅㄢˋㄢˋ",
	"半島": "ㄅㄢˋㄉㄠˇ",
	"半導體": "ㄅㄢˋㄉㄠˇㄊㄧˇ",
	"包袱": "ㄅㄠ_ㄈㄨˊ",
	"包圍": "ㄅㄠ_ㄨㄟˊ",
	"寶貝": "ㄅㄠˇㄅㄟˋ",
	"寶石": "ㄅㄠˇㄕˊ",
	"飽和": "ㄅㄠˇㄏㄜˊ",
	"飽滿": "ㄅㄠˇㄇㄢˇ",
	"保安": "ㄅㄠˇㄢ_",
	"保管": "ㄅㄠˇㄍㄨㄢˇ",
	"保齡球": "ㄅㄠˇㄌㄧㄥˊㄑㄧㄡˊ",
	"保姆": "ㄅㄠˇㄇㄨˇ",
	"保全": "ㄅㄠˇㄑㄩㄢˊ",
	"保險": "ㄅㄠˇㄒㄧㄢˇ",
	"保佑": "ㄅㄠˇㄧㄡˋ",
	"保重": "ㄅㄠˇㄓㄨㄥˋ",
	"報案": "ㄅㄠˋㄢˋ",
	"報表": "ㄅㄠˋㄅㄧㄠˇ",
	"報酬": "ㄅㄠˋㄔㄡˊ",
	"報復": "ㄅㄠˋㄈㄨˋ",
	"報關": "ㄅㄠˋㄍㄨㄢ_",
	"報價": "ㄅㄠˋㄐㄧㄚˋ",
	"報刊": "ㄅㄠˋㄎㄢ_",
	"報應": "ㄅㄠˋㄧㄥˋ",
	"報章": "ㄅㄠˋㄓㄤ_",
	"暴雨": "ㄅㄠˋㄩˇ",
	"爆發": "ㄅㄠˋㄈㄚ_",
	"抱負": "ㄅㄠˋㄈㄨˋ",
	"碑": "ㄅㄟ_",
	"悲哀": "ㄅㄟ_ㄞ_",
	"悲觀": "ㄅㄟ_ㄍㄨㄢ_",
	"貝殼": "ㄅㄟˋㄎㄜˊ",
	"倍數": "ㄅㄟˋㄕㄨˋ",
	"背誦": "ㄅㄟˋㄙㄨㄥˋ",
	"奔騰": "ㄅㄣ_ㄊㄥˊ",
	"本": "ㄅㄣˇ",
	"本事": "ㄅㄣˇㄕˋ",
	"本位": "ㄅㄣˇㄨㄟˋ",
	"本性": "ㄅㄣˇㄒㄧㄥˋ",
	"本質": "ㄅㄣˇㄓˊ",
	"崩潰": "ㄅㄥ_ㄎㄨㄟˋ",
	"甭": "ㄅㄥˊ",
	"敝": "ㄅㄧˋ",
	"必": "ㄅㄧˋ",
	"編輯": "ㄅㄧㄢ_ㄐㄧˊ",
	"編寫": "ㄅㄧㄢ_ㄒㄧㄝˇ",
	"編織": "ㄅㄧㄢ_ㄓ_",
	"編制": "ㄅㄧㄢ_ㄓˋ",
	"編製": "ㄅㄧㄢ_ㄓˋ",
	"邊界": "ㄅㄧㄢ_ㄐㄧㄝˋ",
	"邊緣": "ㄅㄧㄢ_ㄩㄢˊ",
	"貶": "ㄅㄧㄢˇ",
	"貶值": "ㄅㄧㄢˇㄓˊ",
	"匾額": "ㄅㄧㄢˇㄜˊ",
	"辨認": "ㄅㄧㄢˋㄖㄣˋ",
	"辨識": "ㄅㄧㄢˋㄕˋ",
	"辯": "ㄅㄧㄢˋ",
	"辯護": "ㄅㄧㄢˋㄏㄨˋ",
	"辯論": "ㄅㄧㄢˋㄌㄨㄣˋ",
	"變革": "ㄅㄧㄢˋㄍㄜˊ",
	"變遷": "ㄅㄧㄢˋㄑㄧㄢ_",
	"變通": "ㄅㄧㄢˋㄊㄨㄥ_",
	"變形": "ㄅㄧㄢˋㄒㄧㄥˊ",
	"標籤": "ㄅㄧㄠ_ㄑㄧㄢ_",
	"標語": "ㄅㄧㄠ_ㄩˇ",
	"表白": "ㄅㄧㄠˇㄅㄞˊ",
	"表明": "ㄅㄧㄠˇㄇㄧㄥˊ",
	"鼻孔": "ㄅㄧˊㄎㄨㄥˇ",
	"筆錄": "ㄅㄧˇㄌㄨˋ",
	"筆友": "ㄅㄧˇㄧㄡˇ",
	"比率": "ㄅㄧˇㄌㄩˋ",
	"比擬": "ㄅㄧˇㄋㄧˇ",
	"比喻": "ㄅㄧˇㄩˋ",
	"比重": "ㄅㄧˇㄓㄨㄥˋ",
	"必備": "ㄅㄧˋㄅㄟˋ",
	"必定": "ㄅㄧˋㄉㄧㄥˋ",
	"必然": "ㄅㄧˋㄖㄢˊ",
	"閉幕": "ㄅㄧˋㄇㄨˋ",
	"避難": "ㄅㄧˋㄋㄢˋ",
	"避孕": "ㄅㄧˋㄩㄣˋ",
	"畢生": "ㄅㄧˋㄕㄥ_",
	"幣值": "ㄅㄧˋㄓˊ",
	"憋": "ㄅㄧㄝ_",
	"別": "ㄅㄧㄝˊ",
	"別墅": "ㄅㄧㄝˊㄕㄨˋ",
	"兵": "ㄅㄧㄥ_",
	"賓館": "ㄅㄧㄣ_ㄍㄨㄢˇ",
	"柄": "ㄅㄧㄥˇ",
	"並列": "ㄅㄧㄥˋㄌㄧㄝˋ",
	"並重": "ㄅㄧㄥˋㄓㄨㄥˋ",
	"併發": "ㄅㄧㄥˋㄈㄚ_",
	"病床": "ㄅㄧㄥˋㄔㄨㄤˊ",
	"病菌": "ㄅㄧㄥˋㄐㄩㄣˋ",
	"病患": "ㄅㄧㄥˋㄏㄨㄢˋ",
	"波": "ㄅㄛ_",
	"波及": "ㄅㄛ_ㄐㄧˊ",
	"波浪": "ㄅㄛ_ㄌㄤˋ",
	"剝": "ㄅㄛ_",
	"剝削": "ㄅㄛ_ㄒㄧㄠ_",
	"搏鬥": "ㄅㄛˊㄉㄡˋ",
	"播出": "ㄅㄛ_ㄔㄨ_",
	"補給": "ㄅㄨˇㄐㄧˇ",
	"補救": "ㄅㄨˇㄐㄧㄡˋ",
	"哺乳動物": "ㄅㄨˇㄖㄨˇㄉㄨㄥˋㄨˋ",
	"不便": "ㄅㄨˊㄅㄧㄢˋ",
	"不得": "ㄅㄨˋㄉㄜˊ",
	"不等": "ㄅㄨˋㄉㄥˇ",
	"不動產": "ㄅㄨˊㄉㄨㄥˋㄔㄢˇ",
	"不法": "ㄅㄨˋㄈㄚˇ",
	"不凡": "ㄅㄨˋㄈㄢˊ",
	"不妨": "ㄅㄨˋㄈㄤˊ",
	"不公": "ㄅㄨˋㄍㄨㄥ_",
	"不及": "ㄅㄨˋㄐㄧˊ",
	"不禁": "ㄅㄨˋㄐㄧㄣ_",
	"不堪": "ㄅㄨˋㄎㄢ_",
	"不力": "ㄅㄨˊㄌㄧˋ",
	"不料": "ㄅㄨˊㄌㄧㄠˋ",
	"不免": "ㄅㄨˋㄇㄧㄢˇ",
	"不容": "ㄅㄨˋㄖㄨㄥˊ",
	"不時": "ㄅㄨˋㄕˊ",
	"不惜": "ㄅㄨˋㄒㄧˊ",
	"不下": "ㄅㄨˊㄒㄧㄚˋ",
	"不肖": "ㄅㄨˊㄒㄧㄠˋ",
	"不懈": "ㄅㄨˊㄒㄧㄝˋ",
	"不再": "ㄅㄨˊㄗㄞˋ",
	"不致": "ㄅㄨˊㄓˋ",
	"不知不覺": "ㄅㄨˋㄓ_ㄅㄨˋㄐㄩㄝˊ",
	"不至於": "ㄅㄨˊㄓˋㄩˊ",
	"部落": "ㄅㄨˋㄌㄨㄛˋ",
	"部署": "ㄅㄨˋㄕㄨˇ",
	"步調": "ㄅㄨˋㄉㄧㄠˋ",
	"步驟": "ㄅㄨˋㄗㄡˋ",
	"猜測": "ㄘㄞ_ㄘㄜˋ",
	"猜忌": "ㄘㄞ_ㄐㄧˋ",
	"猜想": "ㄘㄞ_ㄒㄧㄤˇ",
	"裁縫": "ㄘㄞˊㄈㄥˊ",
	"裁減": "ㄘㄞˊㄐㄧㄢˇ",
	"財團": "ㄘㄞˊㄊㄨㄢˊ",
	"財政": "ㄘㄞˊㄓㄥˋ",
	"才智": "ㄘㄞˊㄓˋ",
	"採訪": "ㄘㄞˇㄈㄤˇ",
	"採光": "ㄘㄞˇㄍㄨㄤ_",
	"採納": "ㄘㄞˇㄋㄚˋ",
	"採取": "ㄘㄞˇㄑㄩˇ",
	"彩繪": "ㄘㄞˇㄏㄨㄟˋ",
	"餐具": "ㄘㄢ_ㄐㄩˋ",
	"參謀": "ㄘㄢ_ㄇㄡˊ",
	"殘暴": "ㄘㄢˊㄅㄠˋ",
	"殘酷": "ㄘㄢˊㄎㄨˋ",
	"殘殺": "ㄘㄢˊㄕㄚ_",
	"慘重": "ㄘㄢˇㄓㄨㄥˋ",
	"燦爛": "ㄘㄢˋㄌㄢˋ",
	"蒼白": "ㄘㄤ_ㄅㄞˊ",
	"蒼蠅": "ㄘㄤ_ㄧㄥˊ",
	"操縱": "ㄘㄠ_ㄗㄨㄥˋ",
	"草案": "ㄘㄠˇㄢˋ",
	"草叢": "ㄘㄠˇㄘㄨㄥˊ",
	"草率": "ㄘㄠˇㄕㄨㄞˋ",
	"草藥": "ㄘㄠˇㄧㄠˋ",
	"測": "ㄘㄜˋ",
	"策劃": "ㄘㄜˋㄏㄨㄚˋ",
	"差額": "ㄔㄚ_ㄜˊ",
	"插曲": "ㄔㄚ_ㄑㄩˇ",
	"插嘴": "ㄔㄚ_ㄗㄨㄟˇ",
	"茶具": "ㄔㄚˊㄐㄩˋ",
	"察覺": "ㄔㄚˊㄐㄩㄝˊ",
	"查明": "ㄔㄚˊㄇㄧㄥˊ",
	"蟬": "ㄔㄢˊ",
	"饞": "ㄔㄢˊ",
	"潺潺": "ㄔㄢˊㄔㄢˊ",
	"猖獗": "ㄔㄤ_ㄐㄩㄝˊ",
	"長遠": "ㄔㄤˊㄩㄢˇ",
	"場次": "ㄔㄤˇㄘˋ",
	"場面": "ㄔㄤˇㄇㄧㄢˋ",
	"倡導": "ㄔㄤˋㄉㄠˇ",
	"唱腔": "ㄔㄤˋㄑㄧㄤ_",
	"暢銷": "ㄔㄤˋㄒㄧㄠ_",
	"產物": "ㄔㄢˇㄨˋ",
	"產值": "ㄔㄢˇㄓˊ",
	"超速": "ㄔㄠ_ㄙㄨˋ",
	"超脫": "ㄔㄠ_ㄊㄨㄛ_",
	"抄襲": "ㄔㄠ_ㄒㄧˊ",
	"吵嘴": "ㄔㄠˇㄗㄨㄟˇ",
	"車輛": "ㄔㄜ_ㄌㄧㄤˋ",
	"車廂": "ㄔㄜ_ㄒㄧㄤ_",
	"撤回": "ㄔㄜˋㄏㄨㄟˊ",
	"撤銷": "ㄔㄜˋㄒㄧㄠ_",
	"沉默": "ㄔㄣˊㄇㄛˋ",
	"沉思": "ㄔㄣˊㄙ_",
	"沉重": "ㄔㄣˊㄓㄨㄥˋ",
	"塵土": "ㄔㄣˊㄊㄨˇ",
	"承包": "ㄔㄥˊㄅㄠ_",
	"承擔": "ㄔㄥˊㄉㄢ_",
	"承諾": "ㄔㄥˊㄋㄨㄛˋ",
	"成敗": "ㄔㄥˊㄅㄞˋ",
	"成見": "ㄔㄥˊㄐㄧㄢˋ",
	"成就": "ㄔㄥˊㄐㄧㄡˋ",
	"成品": "ㄔㄥˊㄆㄧㄣˇ",
	"成全": "ㄔㄥˊㄑㄩㄢˊ",
	"成效": "ㄔㄥˊㄒㄧㄠˋ",
	"成衣": "ㄔㄥˊㄧ_",
	"成員": "ㄔㄥˊㄩㄢˊ",
	"成長": "ㄔㄥˊㄓㄤˇ",
	"稱號": "ㄔㄥ_ㄏㄠˋ",
	"稱呼": "ㄔㄥ_ㄏㄨ_",
	"撐腰": "ㄔㄥ_ㄧㄠ_",
	"程式": "ㄔㄥˊㄕˋ",
	"呈獻": "ㄔㄥˊㄒㄧㄢˋ",
	"誠心": "ㄔㄥˊㄒㄧㄣ_",
	"誠心誠意": "ㄔㄥˊㄒㄧㄣ_ㄔㄥˊㄧˋ",
	"誠摯": "ㄔㄥˊㄓˋ",
	"吃驚": "ㄔ_ㄐㄧㄥ_",
	"吃苦": "ㄔ_ㄎㄨˇ",
	"吃力": "ㄔ_ㄌㄧˋ",
	"持久": "ㄔˊㄐㄧㄡˇ",
	"持平": "ㄔˊㄆㄧㄥˊ",
	"池子": "ㄔˊㄗ˙",
	"遲鈍": "ㄔˊㄉㄨㄣˋ",
	"充斥": "ㄔㄨㄥ_ㄔˋ",
	"充裕": "ㄔㄨㄥ_ㄩˋ",
	"沖淡": "ㄔㄨㄥ_ㄉㄢˋ",
	"沖天": "ㄔㄨㄥ_ㄊㄧㄢ_",
	"衝動": "ㄔㄨㄥ_ㄉㄨㄥˋ",
	"衝擊": "ㄔㄨㄥ_ㄐㄧˊ",
	"憧憬": "ㄔㄨㄥ_ㄐㄧㄥˇ",
	"重疊": "ㄔㄨㄥˊㄉㄧㄝˊ",
	"崇尚": "ㄔㄨㄥˊㄕㄤˋ",
	"寵愛": "ㄔㄨㄥˇㄞˋ",
	"寵物": "ㄔㄨㄥˇㄨˋ",
	"抽查": "ㄔㄡ_ㄔㄚˊ",
	"抽空": "ㄔㄡ_ㄎㄨㄥˋ",
	"抽象": "ㄔㄡ_ㄒㄧㄤˋ",
	"抽樣": "ㄔㄡ_ㄧㄤˋ",
	"仇恨": "ㄔㄡˊㄏㄣˋ",
	"稠密": "ㄔㄡˊㄇㄧˋ",
	"出超": "ㄔㄨ_ㄔㄠ_",
	"出錯": "ㄔㄨ_ㄘㄨㄛˋ",
	"出發點": "ㄔㄨ_ㄈㄚ_ㄉㄧㄢˇ",
	"出局": "ㄔㄨ_ㄐㄩˊ",
	"出力": "ㄔㄨ_ㄌㄧˋ",
	"出路": "ㄔㄨ_ㄌㄨˋ",
	"出馬": "ㄔㄨ_ㄇㄚˇ",
	"出賣": "ㄔㄨ_ㄇㄞˋ",
	"出面": "ㄔㄨ_ㄇㄧㄢˋ",
	"出名": "ㄔㄨ_ㄇㄧㄥˊ",
	"出品": "ㄔㄨ_ㄆㄧㄣˇ",
	"出示": "ㄔㄨ_ㄕˋ",
	"出手": "ㄔㄨ_ㄕㄡˇ",
	"出頭": "ㄔㄨ_ㄊㄡˊ",
	"出土": "ㄔㄨ_ㄊㄨˇ",
	"出息": "ㄔㄨ_ㄒㄧˊ",
	"出血": "ㄔㄨ_ㄒㄧㄝˇ",
	"初期": "ㄔㄨ_ㄑㄧˊ",
	"儲備": "ㄔㄨˊㄅㄟˋ",
	"除此之外": "ㄔㄨˊㄘˇㄓ_ㄨㄞˋ",
	"鋤頭": "ㄔㄨˊㄊㄡˊ",
	"處方": "ㄔㄨˇㄈㄤ_",
	"處分": "ㄔㄨˇㄈㄣˋ",
	"處境": "ㄔㄨˇㄐㄧㄥˋ",
	"處事": "ㄔㄨˇㄕˋ",
	"處於": "ㄔㄨˇㄩˊ",
	"處女": "ㄔㄨˋㄋㄩˇ",
	"穿梭": "ㄔㄨㄢ_ㄙㄨㄛ_",
	"傳遞": "ㄔㄨㄢˊㄉㄧˋ",
	"傳奇": "ㄔㄨㄢˊㄑㄧˊ",
	"手機": "ㄕㄡˇㄐㄧ_",
	"明年": "ㄇㄧㄥˊㄋㄧㄢˊ",
	"快樂": "ㄎㄨㄞˋㄌㄜˋ",
	"公園": "ㄍㄨㄥ_ㄩㄢˊ",
	"國家": "ㄍㄨㄛˊㄐㄧㄚ_",
	"家人": "ㄐㄧㄚ_ㄖㄣˊ",
	"工作": "ㄍㄨㄥ_ㄗㄨㄛˋ",
	"醫生": "ㄧ_ㄕㄥ_",
	"英文": "ㄧㄥ_ㄨㄣˊ",
	"問題": "ㄨㄣˋㄊㄧˊ",
	"下課": "ㄒㄧㄚˋㄎㄜˋ",
	"說話": "ㄕㄨㄛ_ㄏㄨㄚˋ",
	"考試": "ㄎㄠˇㄕˋ",
	"功課": "ㄍㄨㄥ_ㄎㄜˋ",
	"教室": "ㄐㄧㄠˋㄕˋ",
	"休息": "ㄒㄧㄡ_ㄒㄧˊ",
	"房間": "ㄈㄤˊㄐㄧㄢ_",
	"天氣": "ㄊㄧㄢ_ㄑㄧˋ",
	"空氣": "ㄎㄨㄥ_ㄑㄧˋ",
	"下雨": "ㄒㄧㄚˋㄩˇ",
	"起床": "ㄑㄧˇㄔㄨㄤˊ",
	"方便": "ㄈㄤ_ㄅㄧㄢˋ",
	"睡覺": "ㄕㄨㄟˋㄐㄧㄠˋ",
	"運動": "ㄩㄣˋㄉㄨㄥˋ",
	"走路": "ㄗㄡˇㄌㄨˋ",
	"唱歌": "ㄔㄤˋㄍㄜ_",
	"跳舞": "ㄊㄧㄠˋㄨˇ",
	"介紹": "ㄐㄧㄝˋㄕㄠˋ",
	"地方": "ㄉㄧˋㄈㄤ_",
	"附近": "ㄈㄨˋㄐㄧㄣˋ",
	"計程車": "ㄐㄧˋㄔㄥˊㄔㄜ_",
	"火車": "ㄏㄨㄛˇㄔㄜ_",
	"飛機": "ㄈㄟ_ㄐㄧ_",
	"外國": "ㄨㄞˋㄍㄨㄛˊ",
	"身體": "ㄕㄣ_ㄊㄧˇ",
	"眼睛": "ㄧㄢˇㄐㄧㄥ_",
	"感冒": "ㄍㄢˇㄇㄠˋ",
	"生病": "ㄕㄥ_ㄅㄧㄥˋ",
	"衣服": "ㄧ_ㄈㄨˊ",
	"蛋糕": "ㄉㄢˋㄍㄠ_",
	"麵包": "ㄇㄧㄢˋㄅㄠ_",
	"水果": "ㄕㄨㄟˇㄍㄨㄛˇ",
	"香蕉": "ㄒㄧㄤ_ㄐㄧㄠ_",
	"食物": "ㄕˊㄨˋ",
	"飲料": "ㄧㄣˇㄌㄧㄠˋ",
	"果汁": "ㄍㄨㄛˇㄓ_",
	"家庭": "ㄐㄧㄚ_ㄊㄧㄥˊ",
	"老人": "ㄌㄠˇㄖㄣˊ",
	"年輕": "ㄋㄧㄢˊㄑㄧㄥ_",
	"號碼": "ㄏㄠˋㄇㄚˇ",
	"城市": "ㄔㄥˊㄕˋ",
	"結婚": "ㄐㄧㄝˊㄏㄨㄣ_",
	"高興": "ㄍㄠ_ㄒㄧㄥˋ",
	"緊張": "ㄐㄧㄣˇㄓㄤ_",
	"可愛": "ㄎㄜˇㄞˋ",
	"生氣": "ㄕㄥ_ㄑㄧˋ",
	"難過": "ㄋㄢˊㄍㄨㄛˋ",
	"聰明": "ㄘㄨㄥ_ㄇㄧㄥˊ",
	"相信": "ㄒㄧㄤ_ㄒㄧㄣˋ",
	"經驗": "ㄐㄧㄥ_ㄧㄢˋ",
	"辛苦": "ㄒㄧㄣ_ㄎㄨˇ",
	"願意": "ㄩㄢˋㄧˋ",
	"習慣": "ㄒㄧˊㄍㄨㄢˋ",
	"當然": "ㄉㄤ_ㄖㄢˊ",
	"醫院": "ㄧ_ㄩㄢˋ",
	"公司": "ㄍㄨㄥ_ㄙ_",
	"辦公室": "ㄅㄢˋㄍㄨㄥ_ㄕˋ",
	"工人": "ㄍㄨㄥ_ㄖㄣˊ",
	"護士": "ㄏㄨˋㄕˋ",
	"司機": "ㄙ_ㄐㄧ_",
	"老闆": "ㄌㄠˇㄅㄢˇ",
	"上班": "ㄕㄤˋㄅㄢ_",
	"下班": "ㄒㄧㄚˋㄅㄢ_",
	"能力": "ㄋㄥˊㄌㄧˋ",
	"努力": "ㄋㄨˇㄌㄧˋ",
	"準備": "ㄓㄨㄣˇㄅㄟˋ"
}
